{
  "count": 7,
  "examples": [
    "পূর্ণিমা",
    "আকাশ",
    "টোকিও",
    "রোম",
    "প্যারিস",
    "মোনাকো",
    "সান্তিয়াগো"
  ],
  "ambiguity": {
    "পূর্ণিমা": [
      {
        "entity_id": "ELBN:00004",
        "entity_name": "পূর্ণিমা",
        "description": "চন্দ্রের একটি কলা",
        "ambiguity_data": "পূর্ণিমাচন্দ্রেরএকটিকলা। এটি তখনই ঘটে যখনচাঁদ,পৃথিবীরযে পাশেসূর্যঅবস্থিত তার ঠিক উল্টো পাশে অবস্থান করে। পৃথিবী থেকে দৃশ্যমান চাঁদ এসময় সূর্য দ্বারা পূর্ণভাবে আলোকিত হয় যার ফলে একে একটি পূর্ণ গোলাকার চাকতি রুপে দেখা যায়। তবে এসময়ও প্রকৃতপক্ষে চাঁদের অর্ধেক অংশই আলোকিত হয় কারণ উল্টো দিকটি অনালোকিতই থেকে যায়।[১]",
        "wikipedia_link": "https://bn.wikipedia.org/wiki/পূর্ণিমা"
      }
    ],
    "আকাশ": [
      {
        "entity_id": "ELBN:00025",
        "entity_name": "আকাশ",
        "description": "প্রাকৃতিক দৃশ্য",
        "ambiguity_data": "আকাশহলভূপৃষ্ঠথেকে বাইরের দিকে অবস্থিত অংশবিশেষ।বায়ুমণ্ডলএবংমহাশূন্যওএর অংশ।",
        "wikipedia_link": "https://bn.wikipedia.org/wiki/আকাশ"
      }
    ],
    "টোকিও": [
      {
        "entity_id": "ELBN:00028",
        "entity_name": "টোকিও",
        "description": "চলচ্চিত্র",
        "ambiguity_data": "টোকিও আন্তর্জাতিক চলচ্চিত্র উৎসব১৯৮৫ সালে প্রতিষ্ঠিত একটি আন্তর্জাতিকচলচ্চিত্র উৎসব। ১৯৮৫ সাল থেকে ১৯৯১ সাল পর্যন্ত এটি দ্বিবার্ষিক ও এরপর থেকে বার্ষিকভাবে অনুষ্ঠিত হয়। ফেডারেশন ইন্টারন্যাশনাল দে অ্যাসোসিয়েশন্স দ্য প্রডিউসার্স দ্য ফিল্মস বা এফআইএপিএফ অনুসারে এটি এশিয়ার অন্যতম প্রতিযোগিতামূলক চলচ্চিত্র উৎসব ওসাংহাই আন্তর্জাতিক চলচ্চিত্র উৎসবেরপর এশিয়ার দ্বিতীয় বৃহত্তর চলচ্চিত্র উৎসব, এবং এফআইএপিএফ কর্তৃক স্বীকৃত একমাত্র জাপানি উৎসব।[১][২][৩]",
        "wikipedia_link": "https://bn.wikipedia.org/wiki/টোকিও"
      }
    ],
    "রোম": [
      {
        "entity_id": "ELBN:00032",
        "entity_name": "রোম",
        "description": "ইতিহাস",
        "ambiguity_data": "রোমের ইতিহাসবলতেরোম শহরেরইতিহাস এবংপ্রাচীন রোমসভ্যতার ইতিহাস বোঝানো হয়। রোমের ইতিহাস আধুনিক বিশ্বে গভীর প্রভাব ফেলেছে, বিশেষ করেক্যাথলিক চার্চের ইতিহাসে। এছাড়া,রোমান আইনবহু আধুনিকআইনব্যবস্থাকেপ্রভাবিত করেছে। রোমের ইতিহাসকে কয়েকটি পর্যায়ে ভাগ করা যায়:",
        "wikipedia_link": "https://bn.wikipedia.org/wiki/রোম"
      }
    ],
    "প্যারিস": [
      {
        "entity_id": "ELBN:00034",
        "entity_name": "প্যারিস",
        "description": "চলচ্চিত্র",
        "ambiguity_data": "আ উইমেন অব প্যারিস(ইংরেজি: A Woman of Paris;অনুবাদ:প্যারিসের একজন নারী) হল ১৯২৩ সালে মুক্তিপ্রাপ্ত মার্কিননির্বাক চলচ্চিত্র। এটি রচনা, প্রযোজনা ও পরিচালনা করেছেনচার্লি চ্যাপলিনএবং পরবর্তীতে তিনি এতে সুরারোপও করেছেন। এটিআ উইমেন অব প্যারিস: আ ড্রামা অব ফেটনামেও পরিচিত।[২][৩]এতে প্রধান চরিত্রে অভিনয় করেনএডনা পারভায়েন্সওকার্ল মিলার।",
        "wikipedia_link": "https://bn.wikipedia.org/wiki/প্যারিস"
      }
    ],
    "মোনাকো": [
      {
        "entity_id": "ELBN:00036",
        "entity_name": "মোনাকো",
        "description": "খেলা/অনুষ্ঠান",
        "ambiguity_data": "মোনাকো জাতীয় ফুটবল দল(ইংরেজি:Monaco national football team) হচ্ছে আন্তর্জাতিকফুটবলেমোনাকোরপ্রতিনিধিত্বকারী পুরুষদের জাতীয় দল,[৩]যার সকল কার্যক্রম মোনাকোর ফুটবলের সর্বোচ্চ নিয়ন্ত্রক সংস্থামোনাকীয় ফুটবল ফেডারেশনদ্বারা নিয়ন্ত্রিত হয়। এই দলটি এপর্যন্ত ফুটবলের সর্বোচ্চ সংস্থাফিফারএবং তাদের আঞ্চলিক সংস্থাউয়েফারসদস্যপদ লাভ করতে পারেনি। ২০০১ সালের ১৪শে জুলাই তারিখে, মোনাকো প্রথমবারের মতো আন্তর্জাতিক খেলায় অংশগ্রহণ করেছে;জার্মানিরফ্রাইবুর্গেরঅনুষ্ঠিত উক্ত ম্যাচে মোনাকোতিব্বতকে২–১ গোলের ব্যবধানে পরাজিত করেছে।",
        "wikipedia_link": "https://bn.wikipedia.org/wiki/মোনাকো"
      }
    ],
    "সান্তিয়াগো": [
      {
        "entity_id": "ELBN:00040",
        "entity_name": "সান্তিয়াগো",
        "description": "খেলোয়াড়",
        "ambiguity_data": "সান্তিয়াগো তোমাস হিমেনেস(স্পেনীয়:Santiago Giménez; জন্ম: ১৮ এপ্রিল ২০০১;সান্তিয়াগো হিমেনেসনামে সুপরিচিত) হলেন একজন আর্জেন্টিনীয়–মেক্সিকীয় পেশাদারফুটবল খেলোয়াড়। তিনি বর্তমানে ওলন্দাজ ক্লাবফেইয়ানর্টএবংমেক্সিকো জাতীয় দলেরহয়েআক্রমণভাগের খেলোয়াড়হিসেবে খেলেন। তিনি মূলতকেন্দ্রীয় আক্রমণভাগের খেলোয়াড়হিসেবে খেলেন।",
        "wikipedia_link": "https://bn.wikipedia.org/wiki/সান্তিয়াগো"
      }
    ]
  }
}